joshydev_ml/common/__init__.py
joshydev_ml/common/atari_wrappers.py
joshydev_ml/common/base_class.py
joshydev_ml/common/buffers.py
joshydev_ml/common/callbacks.py
joshydev_ml/common/distributions.py
joshydev_ml/common/env_checker.py
joshydev_ml/common/env_util.py
joshydev_ml/common/evaluation.py
joshydev_ml/common/logger.py
joshydev_ml/common/monitor.py
joshydev_ml/common/noise.py
joshydev_ml/common/off_policy_algorithm.py
joshydev_ml/common/on_policy_algorithm.py
joshydev_ml/common/policies.py
joshydev_ml/common/preprocessing.py
joshydev_ml/common/results_plotter.py
joshydev_ml/common/running_mean_std.py
joshydev_ml/common/save_util.py
joshydev_ml/common/torch_layers.py
joshydev_ml/common/type_aliases.py
joshydev_ml/common/utils.py
joshydev_ml/common/envs/__init__.py
joshydev_ml/common/envs/bit_flipping_env.py
joshydev_ml/common/envs/identity_env.py
joshydev_ml/common/envs/multi_input_envs.py
joshydev_ml/common/sb2_compat/__init__.py
joshydev_ml/common/sb2_compat/rmsprop_tf_like.py
joshydev_ml/common/vec_env/__init__.py
joshydev_ml/common/vec_env/base_vec_env.py
joshydev_ml/common/vec_env/dummy_vec_env.py
joshydev_ml/common/vec_env/stacked_observations.py
joshydev_ml/common/vec_env/subproc_vec_env.py
joshydev_ml/common/vec_env/util.py
joshydev_ml/common/vec_env/vec_check_nan.py
joshydev_ml/common/vec_env/vec_extract_dict_obs.py
joshydev_ml/common/vec_env/vec_frame_stack.py
joshydev_ml/common/vec_env/vec_monitor.py
joshydev_ml/common/vec_env/vec_normalize.py
joshydev_ml/common/vec_env/vec_transpose.py
joshydev_ml/common/vec_env/vec_video_recorder.py
joshydev_ml/gym/__init__.py
joshydev_ml/gym/core.py
joshydev_ml/gym/error.py
joshydev_ml/gym/logger.py
joshydev_ml/gym/version.py
joshydev_ml/gym/envs/__init__.py
joshydev_ml/gym/envs/registration.py
joshydev_ml/gym/envs/box2d/__init__.py
joshydev_ml/gym/envs/box2d/bipedal_walker.py
joshydev_ml/gym/envs/box2d/car_dynamics.py
joshydev_ml/gym/envs/box2d/car_racing.py
joshydev_ml/gym/envs/box2d/lunar_lander.py
joshydev_ml-0.1.8.dist-info/METADATA
joshydev_ml-0.1.8.dist-info/WHEEL
joshydev_ml-0.1.8.dist-info/top_level.txt
joshydev_ml-0.1.8.dist-info/RECORD
