Metadata-Version: 2.1
Name: joshydev-ml
Version: 0.1.8
Summary: Gym And StableBaselines3
Author: JoshyDev
Classifier: Programming Language :: Python :: 3
Classifier: Programming Language :: Python :: 3.6
Classifier: Programming Language :: Python :: 3.7
Classifier: Programming Language :: Python :: 3.8
Classifier: Programming Language :: Python :: 3.9
Requires-Python: >=3.6
Requires-Dist: numpy >=1.18.0
Requires-Dist: cloudpickle >=1.2.0
Requires-Dist: importlib-metadata >=4.8.1 ; python_version < "3.8"
